<node id="2445">
	<attribute name="Is Enabled" value="true" />
	<attribute name="Name" value="walk crouching backward left" />
	<attribute name="Tags"><string value="Untagged" /></attribute>
	<attribute name="Position" value="0 0 0" />
	<attribute name="Rotation" value="1 0 0 0" />
	<attribute name="Scale" value="1 1 1" />
	<node id="2446">
		<attribute name="Is Enabled" value="true" />
		<attribute name="Name" value="mixamorig:Hips" />
		<attribute name="Tags"><string value="Untagged" /></attribute>
		<attribute name="Position" value="0.02230463 0.6617351 0.02667027" />
		<attribute name="Rotation" value="0.9054196 0.04948663 0.4200329 -0.03659052" />
		<attribute name="Scale" value="1 1 1" />
		<node id="2447">
			<attribute name="Is Enabled" value="true" />
			<attribute name="Name" value="mixamorig:LeftUpLeg" />
			<attribute name="Tags"><string value="Untagged" /></attribute>
			<attribute name="Position" value="-0.134003 -0.060396 -0.007268" />
			<attribute name="Rotation" value="0.05175738 -0.04088983 0.5790669 0.8126075" />
			<attribute name="Scale" value="1 1 1" />
			<node id="2448">
				<attribute name="Is Enabled" value="true" />
				<attribute name="Name" value="mixamorig:LeftLeg" />
				<attribute name="Tags"><string value="Untagged" /></attribute>
				<attribute name="Position" value="0 0.410648 0" />
				<attribute name="Rotation" value="0.5032167 -0.8594532 -0.03944296 0.08097804" />
				<attribute name="Scale" value="1 1 1" />
				<node id="2449">
					<attribute name="Is Enabled" value="true" />
					<attribute name="Name" value="mixamorig:LeftFoot" />
					<attribute name="Tags"><string value="Untagged" /></attribute>
					<attribute name="Position" value="0 0.366828 0" />
					<attribute name="Rotation" value="0.8388461 0.5422822 0.0182557 -0.04397901" />
					<attribute name="Scale" value="1 1 1" />
					<node id="2450">
						<attribute name="Is Enabled" value="true" />
						<attribute name="Name" value="mixamorig:LeftToeBase" />
						<attribute name="Tags"><string value="Untagged" /></attribute>
						<attribute name="Position" value="0 0.17808 0" />
						<attribute name="Rotation" value="0.8994816 0.4305118 0.04875026 -0.05670896" />
						<attribute name="Scale" value="1 1 1" />
						<node id="2451">
							<attribute name="Is Enabled" value="true" />
							<attribute name="Name" value="mixamorig:LeftToe_End" />
							<attribute name="Tags"><string value="Untagged" /></attribute>
							<attribute name="Position" value="0 0.072064 0" />
							<attribute name="Rotation" value="1 0 0 0" />
							<attribute name="Scale" value="1 1 1" />
						</node>
					</node>
				</node>
			</node>
		</node>
		<node id="2452">
			<attribute name="Is Enabled" value="true" />
			<attribute name="Name" value="mixamorig:RightUpLeg" />
			<attribute name="Tags"><string value="Untagged" /></attribute>
			<attribute name="Position" value="0.134003 -0.060396 -0.007971" />
			<attribute name="Rotation" value="0.05700516 -0.0370435 0.5965685 0.7996775" />
			<attribute name="Scale" value="1 1 1" />
			<node id="2453">
				<attribute name="Is Enabled" value="true" />
				<attribute name="Name" value="mixamorig:RightLeg" />
				<attribute name="Tags"><string value="Untagged" /></attribute>
				<attribute name="Position" value="0 0.41065 0" />
				<attribute name="Rotation" value="0.67146 -0.739611 -0.005507423 0.04567992" />
				<attribute name="Scale" value="1 1 1" />
				<node id="2454">
					<attribute name="Is Enabled" value="true" />
					<attribute name="Name" value="mixamorig:RightFoot" />
					<attribute name="Tags"><string value="Untagged" /></attribute>
					<attribute name="Position" value="0 0.366697 0" />
					<attribute name="Rotation" value="0.7568309 0.653046 -0.02324261 0.01406152" />
					<attribute name="Scale" value="1 1 1" />
					<node id="2455">
						<attribute name="Is Enabled" value="true" />
						<attribute name="Name" value="mixamorig:RightToeBase" />
						<attribute name="Tags"><string value="Untagged" /></attribute>
						<attribute name="Position" value="0 0.178488 0" />
						<attribute name="Rotation" value="0.9490991 0.3148435 -0.006989858 -0.005980041" />
						<attribute name="Scale" value="1 1 1" />
						<node id="2456">
							<attribute name="Is Enabled" value="true" />
							<attribute name="Name" value="mixamorig:RightToe_End" />
							<attribute name="Tags"><string value="Untagged" /></attribute>
							<attribute name="Position" value="0 0.072675 0" />
							<attribute name="Rotation" value="1 0 0 0" />
							<attribute name="Scale" value="1 1 1" />
						</node>
					</node>
				</node>
			</node>
		</node>
		<node id="2457">
			<attribute name="Is Enabled" value="true" />
			<attribute name="Name" value="mixamorig:Spine" />
			<attribute name="Tags"><string value="Untagged" /></attribute>
			<attribute name="Position" value="0 0.108713 -0.009513999" />
			<attribute name="Rotation" value="0.9837985 0.1594002 -0.04105877 0.07103772" />
			<attribute name="Scale" value="1 1 1" />
			<node id="2458">
				<attribute name="Is Enabled" value="true" />
				<attribute name="Name" value="mixamorig:Spine1" />
				<attribute name="Tags"><string value="Untagged" /></attribute>
				<attribute name="Position" value="0 0.127316 0" />
				<attribute name="Rotation" value="0.9959947 0.06114557 -0.05162288 -0.03988681" />
				<attribute name="Scale" value="1 1 1" />
				<node id="2459">
					<attribute name="Is Enabled" value="true" />
					<attribute name="Name" value="mixamorig:Spine2" />
					<attribute name="Tags"><string value="Untagged" /></attribute>
					<attribute name="Position" value="0 0.145504 0" />
					<attribute name="Rotation" value="0.9954202 0.06820223 -0.05713392 -0.03496868" />
					<attribute name="Scale" value="1 1 1" />
					<node id="2460">
						<attribute name="Is Enabled" value="true" />
						<attribute name="Name" value="mixamorig:LeftShoulder" />
						<attribute name="Tags"><string value="Untagged" /></attribute>
						<attribute name="Position" value="-0.076706 0.142604 -0.003437" />
						<attribute name="Rotation" value="0.41845 0.682103 -0.3947439 0.4514558" />
						<attribute name="Scale" value="1 1 1" />
						<node id="2461">
							<attribute name="Is Enabled" value="true" />
							<attribute name="Name" value="mixamorig:LeftArm" />
							<attribute name="Tags"><string value="Untagged" /></attribute>
							<attribute name="Position" value="-0.002684 0.125835 0.01717" />
							<attribute name="Rotation" value="0.7750846 0.2768407 0.4389335 -0.3604726" />
							<attribute name="Scale" value="1 1 1" />
							<node id="2462">
								<attribute name="Is Enabled" value="true" />
								<attribute name="Name" value="mixamorig:LeftForeArm" />
								<attribute name="Tags"><string value="Untagged" /></attribute>
								<attribute name="Position" value="9.1E-05 0.249383 -0.009081" />
								<attribute name="Rotation" value="0.5097839 0.5968138 0.5220827 -0.3337113" />
								<attribute name="Scale" value="1 1 1" />
								<node id="2463">
									<attribute name="Is Enabled" value="true" />
									<attribute name="Name" value="mixamorig:LeftHand" />
									<attribute name="Tags"><string value="Untagged" /></attribute>
									<attribute name="Position" value="0 0.2481 0" />
									<attribute name="Rotation" value="0.9486812 -0.0172765 0.3156216 -0.009404429" />
									<attribute name="Scale" value="1 1 1" />
									<node id="2464">
										<attribute name="Is Enabled" value="true" />
										<attribute name="Name" value="mixamorig:LeftHandIndex1" />
										<attribute name="Tags"><string value="Untagged" /></attribute>
										<attribute name="Position" value="0.035356 0.102905 0.000834" />
										<attribute name="Rotation" value="0.9797925 0.1737685 -0.0902495 -0.04081869" />
										<attribute name="Scale" value="1 1 1" />
										<node id="2465">
											<attribute name="Is Enabled" value="true" />
											<attribute name="Name" value="mixamorig:LeftHandIndex2" />
											<attribute name="Tags"><string value="Untagged" /></attribute>
											<attribute name="Position" value="-0.000359 0.033391 0" />
											<attribute name="Rotation" value="0.9687409 0.2447651 0.000418453 0.04038557" />
											<attribute name="Scale" value="1 1 1" />
											<node id="2466">
												<attribute name="Is Enabled" value="true" />
												<attribute name="Name" value="mixamorig:LeftHandIndex3" />
												<attribute name="Tags"><string value="Untagged" /></attribute>
												<attribute name="Position" value="0.000171 0.033128 0" />
												<attribute name="Rotation" value="0.9688002 0.2455467 -0.001428026 0.03362922" />
												<attribute name="Scale" value="1 1 1" />
												<node id="2467">
													<attribute name="Is Enabled" value="true" />
													<attribute name="Name" value="mixamorig:LeftHandIndex4" />
													<attribute name="Tags"><string value="Untagged" /></attribute>
													<attribute name="Position" value="0.000189 0.026934 0" />
													<attribute name="Rotation" value="1 0 0 0" />
													<attribute name="Scale" value="1 1 1" />
												</node>
											</node>
										</node>
									</node>
									<node id="2468">
										<attribute name="Is Enabled" value="true" />
										<attribute name="Name" value="mixamorig:LeftHandMiddle1" />
										<attribute name="Tags"><string value="Untagged" /></attribute>
										<attribute name="Position" value="0.01024 0.110656 -0.00072" />
										<attribute name="Rotation" value="0.9793401 0.1725842 -0.09651495 -0.04233784" />
										<attribute name="Scale" value="1 1 1" />
										<node id="2469">
											<attribute name="Is Enabled" value="true" />
											<attribute name="Name" value="mixamorig:LeftHandMiddle2" />
											<attribute name="Tags"><string value="Untagged" /></attribute>
											<attribute name="Position" value="-0.000228 0.034865 0" />
											<attribute name="Rotation" value="0.9204696 0.3867614 0.0004993367 0.05613445" />
											<attribute name="Scale" value="1 1 1" />
											<node id="2470">
												<attribute name="Is Enabled" value="true" />
												<attribute name="Name" value="mixamorig:LeftHandMiddle3" />
												<attribute name="Tags"><string value="Untagged" /></attribute>
												<attribute name="Position" value="0.000114 0.033338 0" />
												<attribute name="Rotation" value="0.927302 0.370996 -0.001370964 0.04971022" />
												<attribute name="Scale" value="1 1 1" />
												<node id="2471">
													<attribute name="Is Enabled" value="true" />
													<attribute name="Name" value="mixamorig:LeftHandMiddle4" />
													<attribute name="Tags"><string value="Untagged" /></attribute>
													<attribute name="Position" value="0.000113 0.027831 0" />
													<attribute name="Rotation" value="1 0 0 0" />
													<attribute name="Scale" value="1 1 1" />
												</node>
											</node>
										</node>
									</node>
									<node id="2472">
										<attribute name="Is Enabled" value="true" />
										<attribute name="Name" value="mixamorig:LeftHandPinky1" />
										<attribute name="Tags"><string value="Untagged" /></attribute>
										<attribute name="Position" value="-0.032618 0.09494 -0.001102" />
										<attribute name="Rotation" value="0.9951174 0.05718228 0.07235307 -0.0351655" />
										<attribute name="Scale" value="1 1 1" />
										<node id="2473">
											<attribute name="Is Enabled" value="true" />
											<attribute name="Name" value="mixamorig:LeftHandPinky2" />
											<attribute name="Tags"><string value="Untagged" /></attribute>
											<attribute name="Position" value="-6E-05 0.027529 0" />
											<attribute name="Rotation" value="0.8998709 0.4309578 -0.001212329 0.06712921" />
											<attribute name="Scale" value="1 1 1" />
											<node id="2474">
												<attribute name="Is Enabled" value="true" />
												<attribute name="Name" value="mixamorig:LeftHandPinky3" />
												<attribute name="Tags"><string value="Untagged" /></attribute>
												<attribute name="Position" value="0.000231 0.025023 0" />
												<attribute name="Rotation" value="0.9616076 0.2727517 7.745306E-05 0.03028998" />
												<attribute name="Scale" value="1 1 1" />
												<node id="2475">
													<attribute name="Is Enabled" value="true" />
													<attribute name="Name" value="mixamorig:LeftHandPinky4" />
													<attribute name="Tags"><string value="Untagged" /></attribute>
													<attribute name="Position" value="-0.000172 0.017931 0" />
													<attribute name="Rotation" value="1 0 0 0" />
													<attribute name="Scale" value="1 1 1" />
												</node>
											</node>
										</node>
									</node>
									<node id="2476">
										<attribute name="Is Enabled" value="true" />
										<attribute name="Name" value="mixamorig:LeftHandRing1" />
										<attribute name="Tags"><string value="Untagged" /></attribute>
										<attribute name="Position" value="-0.012978 0.113293 -0.001384" />
										<attribute name="Rotation" value="0.9875522 0.1521799 -0.01301764 -0.03758296" />
										<attribute name="Scale" value="1 1 1" />
										<node id="2477">
											<attribute name="Is Enabled" value="true" />
											<attribute name="Name" value="mixamorig:LeftHandRing2" />
											<attribute name="Tags"><string value="Untagged" /></attribute>
											<attribute name="Position" value="7.5E-05 0.027489 0" />
											<attribute name="Rotation" value="0.8237497 0.5610843 -0.001871346 0.0813477" />
											<attribute name="Scale" value="1 1 1" />
											<node id="2478">
												<attribute name="Is Enabled" value="true" />
												<attribute name="Name" value="mixamorig:LeftHandRing3" />
												<attribute name="Tags"><string value="Untagged" /></attribute>
												<attribute name="Position" value="0.000108 0.026704 0" />
												<attribute name="Rotation" value="0.9542877 0.2811528 -0.01900468 0.09963413" />
												<attribute name="Scale" value="1 1 1" />
												<node id="2479">
													<attribute name="Is Enabled" value="true" />
													<attribute name="Name" value="mixamorig:LeftHandRing4" />
													<attribute name="Tags"><string value="Untagged" /></attribute>
													<attribute name="Position" value="-0.000183 0.023206 0" />
													<attribute name="Rotation" value="1 0 0 0" />
													<attribute name="Scale" value="1 1 1" />
												</node>
											</node>
										</node>
									</node>
									<node id="2480">
										<attribute name="Is Enabled" value="true" />
										<attribute name="Name" value="mixamorig:LeftHandThumb1" />
										<attribute name="Tags"><string value="Untagged" /></attribute>
										<attribute name="Position" value="0.029847 0.033283 0.01068" />
										<attribute name="Rotation" value="0.960984 0.240862 -0.07338555 -0.1144985" />
										<attribute name="Scale" value="1 1 1" />
										<node id="2481">
											<attribute name="Is Enabled" value="true" />
											<attribute name="Name" value="mixamorig:LeftHandThumb2" />
											<attribute name="Tags"><string value="Untagged" /></attribute>
											<attribute name="Position" value="0.007216 0.036056 0" />
											<attribute name="Rotation" value="0.9997401 0.006795295 0.008777303 0.01991546" />
											<attribute name="Scale" value="1 1 1" />
											<node id="2482">
												<attribute name="Is Enabled" value="true" />
												<attribute name="Name" value="mixamorig:LeftHandThumb3" />
												<attribute name="Tags"><string value="Untagged" /></attribute>
												<attribute name="Position" value="-0.000317 0.036687 0" />
												<attribute name="Rotation" value="0.9342996 -0.1377305 0.07451309 -0.3202536" />
												<attribute name="Scale" value="1 1 1" />
												<node id="2483">
													<attribute name="Is Enabled" value="true" />
													<attribute name="Name" value="mixamorig:LeftHandThumb4" />
													<attribute name="Tags"><string value="Untagged" /></attribute>
													<attribute name="Position" value="-0.006899 0.028474 0" />
													<attribute name="Rotation" value="1 0 0 0" />
													<attribute name="Scale" value="1 1 1" />
												</node>
											</node>
										</node>
									</node>
								</node>
							</node>
						</node>
					</node>
					<node id="2484">
						<attribute name="Is Enabled" value="true" />
						<attribute name="Name" value="mixamorig:Neck" />
						<attribute name="Tags"><string value="Untagged" /></attribute>
						<attribute name="Position" value="0 0.163692 0" />
						<attribute name="Rotation" value="0.9986642 0.001881463 -0.02563423 -0.04482445" />
						<attribute name="Scale" value="1 1 1" />
						<node id="2485">
							<attribute name="Is Enabled" value="true" />
							<attribute name="Name" value="mixamorig:Head" />
							<attribute name="Tags"><string value="Untagged" /></attribute>
							<attribute name="Position" value="0 0.061167 0.024233" />
							<attribute name="Rotation" value="0.9770061 -0.1293978 -0.161194 0.05226585" />
							<attribute name="Scale" value="1 1 1" />
							<node id="2486">
								<attribute name="Is Enabled" value="true" />
								<attribute name="Name" value="mixamorig:HeadTop_End" />
								<attribute name="Tags"><string value="Untagged" /></attribute>
								<attribute name="Position" value="0 0.237128 0.093945" />
								<attribute name="Rotation" value="1 0 0 0" />
								<attribute name="Scale" value="1 1 1" />
							</node>
						</node>
					</node>
					<node id="2487">
						<attribute name="Is Enabled" value="true" />
						<attribute name="Name" value="mixamorig:RightShoulder" />
						<attribute name="Tags"><string value="Untagged" /></attribute>
						<attribute name="Position" value="0.076706 0.142328 -0.000278" />
						<attribute name="Rotation" value="0.4623792 0.5782521 0.4075089 -0.5345713" />
						<attribute name="Scale" value="1 1 1" />
						<node id="2488">
							<attribute name="Is Enabled" value="true" />
							<attribute name="Name" value="mixamorig:RightArm" />
							<attribute name="Tags"><string value="Untagged" /></attribute>
							<attribute name="Position" value="0.009943 0.125671 0.016563" />
							<attribute name="Rotation" value="0.9109313 0.2848899 -0.03563534 0.2962635" />
							<attribute name="Scale" value="1 1 1" />
							<node id="2489">
								<attribute name="Is Enabled" value="true" />
								<attribute name="Name" value="mixamorig:RightForeArm" />
								<attribute name="Tags"><string value="Untagged" /></attribute>
								<attribute name="Position" value="-0.012571 0.249098 -0.008061" />
								<attribute name="Rotation" value="0.5230834 0.1889059 -0.06585667 0.8284692" />
								<attribute name="Scale" value="1 1 1" />
								<node id="2490">
									<attribute name="Is Enabled" value="true" />
									<attribute name="Name" value="mixamorig:RightHand" />
									<attribute name="Tags"><string value="Untagged" /></attribute>
									<attribute name="Position" value="0 0.24812 0" />
									<attribute name="Rotation" value="0.9976656 -0.04382907 -0.05152481 -0.009359907" />
									<attribute name="Scale" value="1 1 1" />
									<node id="2491">
										<attribute name="Is Enabled" value="true" />
										<attribute name="Name" value="mixamorig:RightHandIndex1" />
										<attribute name="Tags"><string value="Untagged" /></attribute>
										<attribute name="Position" value="-0.035021 0.106752 0.000531" />
										<attribute name="Rotation" value="0.9992632 0.03627716 0.001445449 -0.01245203" />
										<attribute name="Scale" value="1 1 1" />
										<node id="2492">
											<attribute name="Is Enabled" value="true" />
											<attribute name="Name" value="mixamorig:RightHandIndex2" />
											<attribute name="Tags"><string value="Untagged" /></attribute>
											<attribute name="Position" value="0.000241 0.033663 0" />
											<attribute name="Rotation" value="0.9948385 0.1003345 -3.740801E-05 -0.0151405" />
											<attribute name="Scale" value="1 1 1" />
											<node id="2493">
												<attribute name="Is Enabled" value="true" />
												<attribute name="Name" value="mixamorig:RightHandIndex3" />
												<attribute name="Tags"><string value="Untagged" /></attribute>
												<attribute name="Position" value="-8.399999E-05 0.03152 0" />
												<attribute name="Rotation" value="0.9571477 0.2879268 0.001150093 -0.03106816" />
												<attribute name="Scale" value="1 1 1" />
												<node id="2494">
													<attribute name="Is Enabled" value="true" />
													<attribute name="Name" value="mixamorig:RightHandIndex4" />
													<attribute name="Tags"><string value="Untagged" /></attribute>
													<attribute name="Position" value="-0.000157 0.025568 0" />
													<attribute name="Rotation" value="1 0 0 0" />
													<attribute name="Scale" value="1 1 1" />
												</node>
											</node>
										</node>
									</node>
									<node id="2495">
										<attribute name="Is Enabled" value="true" />
										<attribute name="Name" value="mixamorig:RightHandMiddle1" />
										<attribute name="Tags"><string value="Untagged" /></attribute>
										<attribute name="Position" value="-0.008599 0.11955 -0.001819" />
										<attribute name="Rotation" value="0.9970593 -0.004322209 0.03085756 -0.07001402" />
										<attribute name="Scale" value="1 1 1" />
										<node id="2496">
											<attribute name="Is Enabled" value="true" />
											<attribute name="Name" value="mixamorig:RightHandMiddle2" />
											<attribute name="Tags"><string value="Untagged" /></attribute>
											<attribute name="Position" value="5E-06 0.030703 0" />
											<attribute name="Rotation" value="0.6215643 0.7790584 0.002818707 -0.08196314" />
											<attribute name="Scale" value="1 1 1" />
											<node id="2497">
												<attribute name="Is Enabled" value="true" />
												<attribute name="Name" value="mixamorig:RightHandMiddle3" />
												<attribute name="Tags"><string value="Untagged" /></attribute>
												<attribute name="Position" value="-0.000252 0.031993 0" />
												<attribute name="Rotation" value="0.8131703 0.5797321 -0.001344028 -0.0516049" />
												<attribute name="Scale" value="1 1 1" />
												<node id="2498">
													<attribute name="Is Enabled" value="true" />
													<attribute name="Name" value="mixamorig:RightHandMiddle4" />
													<attribute name="Tags"><string value="Untagged" /></attribute>
													<attribute name="Position" value="0.000247 0.02136 0" />
													<attribute name="Rotation" value="1 0 0 0" />
													<attribute name="Scale" value="1 1 1" />
												</node>
											</node>
										</node>
									</node>
									<node id="2499">
										<attribute name="Is Enabled" value="true" />
										<attribute name="Name" value="mixamorig:RightHandPinky1" />
										<attribute name="Tags"><string value="Untagged" /></attribute>
										<attribute name="Position" value="0.030382 0.09039 -0.001747" />
										<attribute name="Rotation" value="0.9853063 0.0386228 -0.1587155 -0.04989116" />
										<attribute name="Scale" value="1 1 1" />
										<node id="2500">
											<attribute name="Is Enabled" value="true" />
											<attribute name="Name" value="mixamorig:RightHandPinky2" />
											<attribute name="Tags"><string value="Untagged" /></attribute>
											<attribute name="Position" value="3.1E-05 0.02985 0" />
											<attribute name="Rotation" value="0.6809068 0.7277071 0.001239555 -0.08250286" />
											<attribute name="Scale" value="1 1 1" />
											<node id="2501">
												<attribute name="Is Enabled" value="true" />
												<attribute name="Name" value="mixamorig:RightHandPinky3" />
												<attribute name="Tags"><string value="Untagged" /></attribute>
												<attribute name="Position" value="-0.000121 0.025732 0" />
												<attribute name="Rotation" value="0.7801801 0.6221383 1.025096E-05 -0.06529137" />
												<attribute name="Scale" value="1 1 1" />
												<node id="2502">
													<attribute name="Is Enabled" value="true" />
													<attribute name="Name" value="mixamorig:RightHandPinky4" />
													<attribute name="Tags"><string value="Untagged" /></attribute>
													<attribute name="Position" value="8.899999E-05 0.019043 0" />
													<attribute name="Rotation" value="1 0 0 0" />
													<attribute name="Scale" value="1 1 1" />
												</node>
											</node>
										</node>
									</node>
									<node id="2503">
										<attribute name="Is Enabled" value="true" />
										<attribute name="Name" value="mixamorig:RightHandRing1" />
										<attribute name="Tags"><string value="Untagged" /></attribute>
										<attribute name="Position" value="0.013237 0.124021 0.000864" />
										<attribute name="Rotation" value="0.9876317 0.08557946 -0.1131149 -0.06681965" />
										<attribute name="Scale" value="1 1 1" />
										<node id="2504">
											<attribute name="Is Enabled" value="true" />
											<attribute name="Name" value="mixamorig:RightHandRing2" />
											<attribute name="Tags"><string value="Untagged" /></attribute>
											<attribute name="Position" value="-3.1E-05 0.025134 0" />
											<attribute name="Rotation" value="0.5433624 0.834792 0.001892936 -0.08874717" />
											<attribute name="Scale" value="1 1 1" />
											<node id="2505">
												<attribute name="Is Enabled" value="true" />
												<attribute name="Name" value="mixamorig:RightHandRing3" />
												<attribute name="Tags"><string value="Untagged" /></attribute>
												<attribute name="Position" value="-7.9E-05 0.023471 0" />
												<attribute name="Rotation" value="0.7727551 0.631576 -0.001237918 -0.06292603" />
												<attribute name="Scale" value="1 1 1" />
												<node id="2506">
													<attribute name="Is Enabled" value="true" />
													<attribute name="Name" value="mixamorig:RightHandRing4" />
													<attribute name="Tags"><string value="Untagged" /></attribute>
													<attribute name="Position" value="0.00011 0.016139 0" />
													<attribute name="Rotation" value="1 0 0 0" />
													<attribute name="Scale" value="1 1 1" />
												</node>
											</node>
										</node>
									</node>
									<node id="2507">
										<attribute name="Is Enabled" value="true" />
										<attribute name="Name" value="mixamorig:RightHandThumb1" />
										<attribute name="Tags"><string value="Untagged" /></attribute>
										<attribute name="Position" value="-0.030414 0.033609 0.01238" />
										<attribute name="Rotation" value="0.955722 0.1764616 0.2031165 0.1191658" />
										<attribute name="Scale" value="1 1 1" />
										<node id="2508">
											<attribute name="Is Enabled" value="true" />
											<attribute name="Name" value="mixamorig:RightHandThumb2" />
											<attribute name="Tags"><string value="Untagged" /></attribute>
											<attribute name="Position" value="-0.007702 0.036793 0" />
											<attribute name="Rotation" value="0.9980081 -0.001952855 -0.01891555 -0.06015262" />
											<attribute name="Scale" value="1 1 1" />
											<node id="2509">
												<attribute name="Is Enabled" value="true" />
												<attribute name="Name" value="mixamorig:RightHandThumb3" />
												<attribute name="Tags"><string value="Untagged" /></attribute>
												<attribute name="Position" value="0.002163 0.03575 0" />
												<attribute name="Rotation" value="0.9767444 -0.1459797 -0.02361866 -0.1552502" />
												<attribute name="Scale" value="1 1 1" />
												<node id="2510">
													<attribute name="Is Enabled" value="true" />
													<attribute name="Name" value="mixamorig:RightHandThumb4" />
													<attribute name="Tags"><string value="Untagged" /></attribute>
													<attribute name="Position" value="0.005539 0.027363 0" />
													<attribute name="Rotation" value="1 0 0 0" />
													<attribute name="Scale" value="1 1 1" />
												</node>
											</node>
										</node>
									</node>
								</node>
							</node>
						</node>
					</node>
				</node>
			</node>
		</node>
	</node>
</node>
